Workbook

Sheet Unit Economics
A1: YARNNN — Unit Economics Model
A3: Per-User Cost Breakdown (Monthly)
B4: Free | C4: Starter ($9) | D4: Pro ($19)
A5: Platform sync cost | B5: 0.05 | C5: 0.15 | D5: 0.5
A6: LLM cost (TP conversations) | B6: 0.5 | C6: 2 | D6: 5
A7: Vector storage/compute | B7: 0.02 | C7: 0.08 | D7: 0.2
A8: Infrastructure (allocated) | B8: 0.1 | C8: 0.1 | D8: 0.1
A9: Total COGS per user | B9: =SUM(B5:B8) -> 0.67 | C9: =SUM(C5:C8) -> 2.33 | D9: =SUM(D5:D8) -> 5.8
A11: Revenue per user | B11: 0 | C11: 9 | D11: 19
A12: Gross profit per user | B12: =B11-B9 -> -0.67 | C12: =C11-C9 -> 6.67 | D12: =D11-D9 -> 13.2
A13: Gross margin % | B13: =IF(B11=0,0,B12/B11) -> 0 | C13: =IF(C11=0,0,C12/C11) -> 0.74111111 | D13: =IF(D11=0,0,D12/D11) -> 0.69473684
A15: Sources & Assumptions:
A16: Sync cost: ADR-053 (~$0.003/user/day base, scales with frequency)
A17: LLM cost: Claude API pricing, avg tokens per conversation/deliverable
A18: Vector storage: pgvector on Supabase, estimated per-user allocation
A19: Infrastructure: Render services allocated across user base
A21: Blended Unit Economics (by tier mix)
A22: Assumed tier mix:
A23: Free % | B23: 0.6
A24: Starter % | B24: 0.25
A25: Pro % | B25: 0.15
A27: Blended ARPU | B27: =B23*B11+B24*C11+B25*D11 -> 5.1
A28: Blended COGS per user | B28: =B23*B9+B24*C9+B25*D9 -> 1.8545
A29: Blended gross margin | B29: =IF(B27=0,0,(B27-B28)/B27) -> 0.63637255

Sheet Revenue Projections
A1: YARNNN — 3-Year Revenue Projections
A3: User Growth
A4: Metric | B4: Q1'26 | C4: Q2'26 | D4: Q3'26 | E4: Q4'26 | F4: Q1'27 | G4: Q2'27 | H4: Q3'27 | I4: Q4'27 | J4: Q1'28 | K4: Q2'28 | L4: Q3'28 | M4: Q4'28 | N4: FY2026 | O4: FY2027 | P4: FY2028
A5: New signups (quarterly) | B5: 50 | C5: 150 | D5: 400 | E5: 800 | F5: 1500 | G5: 2500 | H5: 4000 | I5: 6000 | J5: 8000 | K5: 10000 | L5: 12000 | M5: 15000 | N5: =B5+C5+D5+E5 -> 1400 | O5: =F5+G5+H5+I5 -> 14000 | P5: =J5+K5+L5+M5 -> 45000
A6: Monthly churn rate | B6: 0.15 | C6: 0.12 | D6: 0.1 | E6: 0.08 | F6: 0.07 | G6: 0.06 | H6: 0.055 | I6: 0.05 | J6: 0.045 | K6: 0.04 | L6: 0.04 | M6: 0.035
A7: Churned users (quarterly) | B7: =ROUND(B6*3*0,0) -> 0 | C7: =ROUND(C6*3*B8,0) -> 18 | D7: =ROUND(D6*3*C8,0) -> 55 | E7: =ROUND(E6*3*D8,0) -> 126 | F7: =ROUND(F6*3*E8,0) -> 252 | G7: =ROUND(G6*3*F8,0) -> 441 | H7: =ROUND(H6*3*G8,0) -> 744 | I7: =ROUND(I6*3*H8,0) -> 1165 | J7: =ROUND(J6*3*I8,0) -> 1701 | ... M7: =ROUND(M6*3*L8,0) -> 3721 | N7: =B7+C7+D7+E7 -> 199 | O7: =F7+G7+H7+I7 -> 2602 | P7: =J7+K7+L7+M7 -> 10886
A8: Total active users (EoQ) | B8: =B5-B7 -> 50 | C8: =B8+C5-C7 -> 182 | D8: =C8+D5-D7 -> 527 | E8: =D8+E5-E7 -> 1201 | F8: =E8+F5-F7 -> 2449 | G8: =F8+G5-G7 -> 4508 | H8: =G8+H5-H7 -> 7764 | I8: =H8+I5-I7 -> 12599 | J8: =I8+J5-J7 -> 18898 | ... M8: =L8+M5-M7 -> 46713 | N8: =E8 -> 1201 | O8: =I8 -> 12599 | P8: =M8 -> 46713
A10: Revenue ($)
A11: Metric | B11: Q1'26 | C11: Q2'26 | D11: Q3'26 | E11: Q4'26 | F11: Q1'27 | G11: Q2'27 | H11: Q3'27 | I11: Q4'27 | J11: Q1'28 | K11: Q2'28 | L11: Q3'28 | M11: Q4'28 | N11: FY2026 | O11: FY2027 | P11: FY2028
A12: Paying users (Starter+Pro) | B12: =ROUND(B8*(1-'Unit Economics'!B23),0) -> 20 | C12: =ROUND(C8*(1-'Unit Economics'!B23),0) -> 73 | D12: =ROUND(D8*(1-'Unit Economics'!B23),0) -> 211 | E12: =ROUND(E8*(1-'Unit Economics'!B23),0) -> 480 | F12: =ROUND(F8*(1-'Unit Economics'!B23),0) -> 980 | G12: =ROUND(G8*(1-'Unit Economics'!B23),0) -> 1803 | H12: =ROUND(H8*(1-'Unit Economics'!B23),0) -> 3106 | I12: =ROUND(I8*(1-'Unit Economics'!B23),0) -> 5040 | J12: =ROUND(J8*(1-'Unit Economics'!B23),0) -> 7559 | K12: =ROUND(K8*(1-'Unit Economics'!B23),0) -> 10652 | L12: =ROUND(L8*(1-'Unit Economics'!B23),0) -> 14174 | M12: =ROUND(M8*(1-'Unit Economics'!B23),0) -> 18685
A13: MRR (monthly recurring) | B13: =B8*'Unit Economics'!B27 -> 255 | C13: =C8*'Unit Economics'!B27 -> 928.2 | D13: =D8*'Unit Economics'!B27 -> 2687.7 | E13: =E8*'Unit Economics'!B27 -> 6125.1 | F13: =F8*'Unit Economics'!B27 -> 12489.9 | G13: =G8*'Unit Economics'!B27 -> 22990.8 | H13: =H8*'Unit Economics'!B27 -> 39596.4 | I13: =I8*'Unit Economics'!B27 -> 64254.9 | J13: =J8*'Unit Economics'!B27 -> 96379.8 | K13: =K8*'Unit Economics'!B27 -> 135813 | L13: =L8*'Unit Economics'!B27 -> 180713.4 | M13: =M8*'Unit Economics'!B27 -> 238236.3
A14: Quarterly revenue | B14: =B13*3 -> 765 | C14: =C13*3 -> 2784.6 | D14: =D13*3 -> 8063.1 | E14: =E13*3 -> 18375.3 | F14: =F13*3 -> 37469.7 | G14: =G13*3 -> 68972.4 | H14: =H13*3 -> 118789.2 | I14: =I13*3 -> 192764.7 | ... M14: =M13*3 -> 714708.9 | N14: =B14+C14+D14+E14 -> 29988 | O14: =F14+G14+H14+I14 -> 417996 | P14: =J14+K14+L14+M14 -> 1953427.5
A15: ARR (annualized from EoQ MRR) | B15: =B13*12 -> 3060 | C15: =C13*12 -> 11138.4 | D15: =D13*12 -> 32252.4 | E15: =E13*12 -> 73501.2 | F15: =F13*12 -> 149878.8 | G15: =G13*12 -> 275889.6 | H15: =H13*12 -> 475156.8 | I15: =I13*12 -> 771058.8 | ... M15: =M13*12 -> 2858835.6 | N15: =E15 -> 73501.2 | O15: =I15 -> 771058.8 | P15: =M15 -> 2858835.6
A17: COGS & Gross Profit
A18: Total COGS (quarterly) | B18: =B8*'Unit Economics'!B28*3 -> 278.175 | C18: =C8*'Unit Economics'!B28*3 -> 1012.557 | D18: =D8*'Unit Economics'!B28*3 -> 2931.9645 | E18: =E8*'Unit Economics'!B28*3 -> 6681.7635 | F18: =F8*'Unit Economics'!B28*3 -> 13625.012 | G18: =G8*'Unit Economics'!B28*3 -> 25080.258 | H18: =H8*'Unit Economics'!B28*3 -> 43195.014 | I18: =I8*'Unit Economics'!B28*3 -> 70094.537 | J18: =J8*'Unit Economics'!B28*3 -> 105139.02 | K18: =K8*'Unit Economics'!B28*3 -> 148156.01 | L18: =L8*'Unit Economics'!B28*3 -> 197137.06 | M18: =M8*'Unit Economics'!B28*3 -> 259887.78 | N18: =B18+C18+D18+E18 -> 10904.46 | O18: =F18+G18+H18+I18 -> 151994.82 | P18: =J18+K18+L18+M18 -> 710319.86
A19: Gross profit (quarterly) | B19: =B14-B18 -> 486.825 | C19: =C14-C18 -> 1772.043 | D19: =D14-D18 -> 5131.1355 | E19: =E14-E18 -> 11693.537 | F19: =F14-F18 -> 23844.689 | G19: =G14-G18 -> 43892.142 | H19: =H14-H18 -> 75594.186 | I19: =I14-I18 -> 122670.16 | ... M19: =M14-M18 -> 454821.12 | N19: =B19+C19+D19+E19 -> 19083.54 | O19: =F19+G19+H19+I19 -> 266001.18 | P19: =J19+K19+L19+M19 -> 1243107.6
A20: Gross margin % | B20: =IF(B14=0,0,B19/B14) -> 0.63637255 | C20: =IF(C14=0,0,C19/C14) -> 0.63637255 | D20: =IF(D14=0,0,D19/D14) -> 0.63637255 | E20: =IF(E14=0,0,E19/E14) -> 0.63637255 | F20: =IF(F14=0,0,F19/F14) -> 0.63637255 | G20: =IF(G14=0,0,G19/G14) -> 0.63637255 | H20: =IF(H14=0,0,H19/H14) -> 0.63637255 | I20: =IF(I14=0,0,I19/I14) -> 0.63637255 | ... M20: =IF(M14=0,0,M19/M14) -> 0.63637255

Sheet Burn & Runway
A1: YARNNN — Burn Rate & Runway Model
A3: Funding Assumptions
A4: Seed raise amount | B4: 750000
A5: Pre-money valuation | B5: 7500000
A6: Dilution % | B6: =B4/(B5+B4) -> 0.090909091
A8: Monthly Operating Expenses
A9: Expense Category | B9: Q1'26 | C9: Q2'26 | D9: Q3'26 | E9: Q4'26 | F9: Q1'27 | G9: Q2'27 | H9: Q3'27 | I9: Q4'27 | J9: Q1'28 | K9: Q2'28 | L9: Q3'28 | M9: Q4'28 | N9: FY2026 | O9: FY2027 | P9: FY2028
A10: Founder salary (monthly) | B10: 0 | C10: 0 | D10: 5000 | E10: 5000 | F10: 5000 | G10: 5000 | H10: 6000 | I10: 6000 | J10: 7000 | K10: 7000 | L10: 8000 | M10: 8000
A11: Tech Lead (monthly) | B11: 0 | C11: 0 | D11: 0 | E11: 12000 | F11: 12000 | G11: 12000 | H11: 12000 | I11: 13000 | J11: 13000 | K11: 13000 | L11: 14000 | M11: 14000
A12: GTM Lead (monthly) | B12: 0 | C12: 0 | D12: 0 | E12: 0 | F12: 8000 | G12: 8000 | H12: 8000 | I12: 9000 | J12: 9000 | K12: 9000 | L12: 10000 | M12: 10000
A13: Infrastructure (Render, Supabase, APIs) | B13: 200 | C13: 300 | D13: 500 | E13: 800 | F13: 1200 | G13: 1800 | H13: 2500 | I13: 3500 | J13: 4500 | K13: 5500 | L13: 6500 | M13: 8000
A14: Other (legal, tools, misc) | B14: 300 | C14: 300 | D14: 500 | E14: 500 | F14: 800 | G14: 800 | H14: 1000 | I14: 1000 | J14: 1200 | K14: 1200 | L14: 1500 | M14: 1500
A16: Quarterly OpEx (salaries * 3 + infra*3 + other*3) | B16: =(B10+B11+B12+B13+B14)*3 -> 1500 | C16: =(C10+C11+C12+C13+C14)*3 -> 1800 | D16: =(D10+D11+D12+D13+D14)*3 -> 18000 | E16: =(E10+E11+E12+E13+E14)*3 -> 54900 | F16: =(F10+F11+F12+F13+F14)*3 -> 81000 | G16: =(G10+G11+G12+G13+G14)*3 -> 82800 | H16: =(H10+H11+H12+H13+H14)*3 -> 88500 | I16: =(I10+I11+I12+I13+I14)*3 -> 97500 | ... M16: =(M10+M11+M12+M13+M14)*3 -> 124500 | N16: =B16+C16+D16+E16 -> 76200 | O16: =F16+G16+H16+I16 -> 349800 | P16: =J16+K16+L16+M16 -> 455700
A18: Cash Flow
A19: Revenue (from projections) | B19: ='Revenue Projections'!B14 -> 765 | C19: ='Revenue Projections'!C14 -> 2784.6 | D19: ='Revenue Projections'!D14 -> 8063.1 | E19: ='Revenue Projections'!E14 -> 18375.3 | F19: ='Revenue Projections'!F14 -> 37469.7 | G19: ='Revenue Projections'!G14 -> 68972.4 | H19: ='Revenue Projections'!H14 -> 118789.2 | I19: ='Revenue Projections'!I14 -> 192764.7 | ... M19: ='Revenue Projections'!M14 -> 714708.9 | N19: =B19+C19+D19+E19 -> 29988 | O19: =F19+G19+H19+I19 -> 417996 | P19: =J19+K19+L19+M19 -> 1953427.5
A20: COGS (from projections) | B20: ='Revenue Projections'!B18 -> 278.175 | C20: ='Revenue Projections'!C18 -> 1012.557 | D20: ='Revenue Projections'!D18 -> 2931.9645 | E20: ='Revenue Projections'!E18 -> 6681.7635 | F20: ='Revenue Projections'!F18 -> 13625.012 | G20: ='Revenue Projections'!G18 -> 25080.258 | H20: ='Revenue Projections'!H18 -> 43195.014 | I20: ='Revenue Projections'!I18 -> 70094.537 | ... M20: ='Revenue Projections'!M18 -> 259887.78 | N20: =B20+C20+D20+E20 -> 10904.46 | O20: =F20+G20+H20+I20 -> 151994.82 | P20: =J20+K20+L20+M20 -> 710319.86
A21: Total spend (OpEx + COGS) | B21: =B16+B20 -> 1778.175 | C21: =C16+C20 -> 2812.557 | D21: =D16+D20 -> 20931.964 | E21: =E16+E20 -> 61581.764 | F21: =F16+F20 -> 94625.011 | G21: =G16+G20 -> 107880.26 | H21: =H16+H20 -> 131695.01 | I21: =I16+I20 -> 167594.54 | ... M21: =M16+M20 -> 384387.78 | N21: =B21+C21+D21+E21 -> 87104.46 | O21: =F21+G21+H21+I21 -> 501794.82 | P21: =J21+K21+L21+M21 -> 1166019.9
A22: Net burn (quarterly) | B22: =B19-B21 -> -1013.175 | C22: =C19-C21 -> -27.957 | D22: =D19-D21 -> -12868.864 | E22: =E19-E21 -> -43206.463 | F22: =F19-F21 -> -57155.312 | G22: =G19-G21 -> -38907.858 | H22: =H19-H21 -> -12905.814 | I22: =I19-I21 -> 25170.163 | ... M22: =M19-M21 -> 330321.12 | N22: =B22+C22+D22+E22 -> -57116.46 | O22: =F22+G22+H22+I22 -> -83798.82 | P22: =J22+K22+L22+M22 -> 787407.64
A24: Cash balance (EoQ) | B24: =B4+B22 -> 748986.82 | C24: =B24+C22 -> 748958.87 | D24: =C24+D22 -> 736090 | E24: =D24+E22 -> 692883.54 | F24: =E24+F22 -> 635728.23 | G24: =F24+G22 -> 596820.37 | H24: =G24+H22 -> 583914.56 | I24: =H24+I22 -> 609084.72 | J24: =I24+J22 -> 688985.1 | ... M24: =L24+M22 -> 1396492.4
A25: Months runway remaining | B25: =IF(B22>=0,"∞",B24/(-B22/3)) -> 2217.7417 | C25: =IF(C22>=0,"∞",C24/(-C22/3)) -> 80369.017 | D25: =IF(D22>=0,"∞",D24/(-D22/3)) -> 171.59789 | E25: =IF(E22>=0,"∞",E24/(-E22/3)) -> 48.109714 | F25: =IF(F22>=0,"∞",F24/(-F22/3)) -> 33.368459 | G25: =IF(G22>=0,"∞",G24/(-G22/3)) -> 46.017982 | H25: =IF(H22>=0,"∞",H24/(-H22/3)) -> 135.73291 | I25: =IF(I22>=0,"∞",I24/(-I22/3)) -> ∞ | ... M25: =IF(M22>=0,"∞",M24/(-M22/3)) -> ∞

Sheet TAM SAM SOM
A1: YARNNN — Market Sizing Sources
A3: TAM: AI Productivity Tools
A4: Metric | B4: Value | C4: Source | D4: Date
A5: AI productivity market size | B5: $4.35B | C5: Grand View Research — AI in workplace productivity | D5: 2025
A6: Market CAGR | B6: 31% | C6: Grand View Research | D6: 2025-2030
A7: Projected 2030 market | B7: $21.5B | C7: Grand View Research | D7: 2030 est.
A8: AI creator tools segment | B8: $1.3B | C8: Goldman Sachs Creator Economy Report | D8: 2025
A9: Creator economy total | B9: $480B by 2027 | C9: Goldman Sachs | D9: 2024 report
A11: SAM: Solo Consultants
A12: Metric | B12: Value | C12: Source | D12: Date
A13: Global freelancers | B13: 1.57B | C13: DemandSage Global Freelance Statistics | D13: 2025
A14: US independent consultants | B14: ~6.9M | C14: MBO Partners State of Independence | D14: 2024
A15: Global management consultants | B15: ~5M (est) | C15: IBIS World + Statista extrapolation | D15: 2024
A16: % with recurring client obligations | B16: ~60% | C16: MBO Partners survey data | D16: 2024
A17: Addressable consultant base | B17: ~3M | C17: 5M × 60% recurring work | D17: Calculated
A18: Pro annual price | B18: $228/yr | C18: $19/mo × 12 | D18: yarnnn pricing
A19: SAM calculation | B19: $684M | C19: 3M × $228/yr | D19: Calculated
A20: Expanded SAM (incl. founders/execs) | B20: $1.14B | C20: ~5M professionals × $228/yr | D20: Calculated
A22: SOM: Entry Wedge (3-Year Target)
A23: Metric | B23: Value | C23: Source | D23: Date
A24: Target: solo consultants (US first) | B24: ~2M | C24: MBO Partners + BLS data | D24: 2024
A25: Realistic penetration (3 years) | B25: 1% | C25: Conservative for new category | D25: Assumption
A26: Target paid users | B26: 20,000 | C26: 2M × 1% | D26: Calculated
A27: Blended ARPU (annual) | B27: $171 | C27: Mix of Starter + Pro | D27: From Unit Economics
A28: Entry SOM | B28: $3.4M ARR | C28: 20K × $171 | D28: Calculated
A29: Stretch SOM (50K users) | B29: $8.6M ARR | C29: Achievable with strong GTM | D29: Stretch target
A31: Expansion Path
A32: Phase 1: Solo consultants | B32: ~3M globally | C32: Recurring client reports, clear pain
A33: Phase 2: Founders & executives | B33: ~2M globally | C33: Investor updates, board prep, briefs
A34: Phase 3: Teams & ops leads | B34: ~10M globally | C34: Standups, project reports, cross-team
A35: Phase 4: All knowledge workers | B35: ~50M+ globally | C35: Any recurring work obligation
A37: Competitive Valuation Comps
A38: Company | B38: Valuation | C38: Category | D38: What yarnnn adds
A39: Notion | B39: $11B | C39: Productivity | D39: No autonomous output, single-platform
A40: Glean | B40: $7.2B | C40: Enterprise Search | D40: Enterprise-only, no prosumer play
A41: Granola | B41: $250M | C41: AI Notes | D41: Meeting-only, no cross-platform synthesis
A42: Mem.ai | B42: $110M (OpenAI-backed) | C42: Second Brain | D42: Memory without autonomous work output
A43: TwinMind | B43: $60M (Seed, Sep 2025) | C43: AI Memory | D43: Memory layer only, no deliverable engine
A44: Limitless | B44: Acquired by Meta | C44: AI Memory | D44: Acquired for memory tech alone

Sheet Operating Plan
A1: YARNNN — 18-Month Operating Plan
A2: Seed round: $500K–$1M | Target: 18 months runway
A4: Milestone Timeline
A5: Milestone | B5: Months 1-3 | C5: Months 4-6 | D5: Months 7-9 | E5: Months 10-12 | F5: Months 13-15 | G5: Months 16-18 | H5: Success Metric
A6: Users | B6: 50 beta | C6: 200 active | D6: 800 active | E6: 2,000 active | F6: 5,000 active | G6: 10,000 active | H6: 30-day retention > 40%
A7: Revenue | B7: $0 (beta) | C7: $1K MRR | D7: $5K MRR | E7: $15K MRR | F7: $35K MRR | G7: $70K MRR | H7: Path to $100K MRR
A8: Product | B8: TP + 4 integrations | C8: Deliverable engine v2 | D8: Signal processing | E8: Team features (alpha) | F8: API / plugin system | G8: Enterprise pilot | H8: NPS > 50
A9: Team | B9: Solo founder | C9: Tech Lead hired | D9: GTM Lead hired | E9: 3 people | F9: 4-5 people | G9: 5-6 people | H9: Key hires in place
A10: Fundraise | B10: Seed closes | C10: — | D10: Series A prep | E10: Series A conversations | F10: Series A close ($3-5M) | G10: — | H10: $3-5M at $30-50M
A13: Use of Funds Allocation ($750K midpoint)
A14: Category | B14: Amount | C14: % of Total | D14: Notes
A15: Founder salary (18 mo) | B15: 90000 | C15: =B15/750000 -> 0.12 | D15: Pre-revenue: $0, scales to $8K/mo
A16: Tech Lead (12 mo) | B16: 156000 | C16: =B16/750000 -> 0.208 | D16: Hired month 4, $12-14K/mo
A17: GTM Lead (10 mo) | B17: 90000 | C17: =B17/750000 -> 0.12 | D17: Hired month 7, $8-10K/mo
A18: Infrastructure & APIs | B18: 54000 | C18: =B18/750000 -> 0.072 | D18: Render, Supabase, Claude API, scaling with users
A19: Legal & compliance | B19: 30000 | C19: =B19/750000 -> 0.04 | D19: Incorporation, IP, privacy policy, terms
A20: Tools & software | B20: 18000 | C20: =B20/750000 -> 0.024 | D20: Dev tools, analytics, marketing tools
A21: Buffer / contingency | B21: 312000 | C21: =B21/750000 -> 0.416 | D21: Runway extension, unexpected costs
A22: TOTAL | B22: =SUM(B15:B21) -> 750000 | C22: =SUM(C15:C21) -> 1
A24: Key Hypotheses Being Tested
A25: Hypothesis | B25: What We're Testing | C25: Success Metric
A26: H1: Cold-start solved by TP | B26: TP with synced platform context provides immediate value from Day 1 | C26: Week 1 retention > 60%
A27: H2: Context compounds value | B27: Accumulated context produces measurably better output over time | C27: Edit distance decreases 30%+ by week 8
A28: H3: Switching costs are real | B28: Users with 90+ days of context don't churn to competitors | C28: 90-day retention > 70%
A29: H4: Consultants will pay $19/mo | B29: Solo consultants see enough value to upgrade from free | C29: Free→paid conversion > 8%
